setup.py
file_manager/__init__.py
file_manager/asgi.py
file_manager/settings.py
file_manager/urls.py
file_manager/wsgi.py
file_manipulation/__init__.py
file_manipulation/comment.py
file_manipulation/delete.py
file_manipulation/find_in_file.py
file_manipulation/insert.py
file_manipulation/read_file.py
file_manipulation/replace.py
file_manipulation/uncomment.py
file_manipulation.egg-info/PKG-INFO
file_manipulation.egg-info/SOURCES.txt
file_manipulation.egg-info/dependency_links.txt
file_manipulation.egg-info/top_level.txt