Metadata-Version: 2.1
Name: file-manipulation
Version: 1.0
Summary: A Python package for managing files
